loubach/__init__.py
loubach/error.py
loubach/data/__init__.py
loubach/data/load.py
loubach/instrument/__init__.py
loubach/instrument/equity.py
loubach/instrument/instrument.py
loubach/instrument/other.py
loubach/math/__init__.py
loubach/math/series.py
loubach/math/stats.py
loubach/math/technicals.py
loubach/math/trend.py
loubach/portfolio/__init__.py
loubach/portfolio/holding.py
loubach/portfolio/portfolio.py
loubach/timeseries/__init__.py
loubach/timeseries/priceable_ts.py
loubach/types/__init__.py
loubach/types/priceable.py
loubach/types/qtime.py
loubach/types/sector.py
loubach/types/time.py
loubach-1.0.dist-info/METADATA
loubach-1.0.dist-info/WHEEL
loubach-1.0.dist-info/top_level.txt
loubach-1.0.dist-info/RECORD
