Metadata-Version: 2.4
Name: loubach
Version: 1.0
Summary: A Python toolkit for quantitative market analysis
Home-page: https://github.com/p-korolev/Loubach
Author: Phillip Korolev
Author-email: p.korolev1@outlook.com
License: MIT
Requires-Python: >=3.9
Requires-Dist: numpy>=1.26.0
Requires-Dist: pandas>=2.2.0
Requires-Dist: matplotlib>=3.9.0
Requires-Dist: seaborn>=0.13.0
Requires-Dist: mplfinance>=0.12.10b0
Requires-Dist: scipy>=1.13.0
Requires-Dist: yfinance>=0.2.40
Requires-Dist: plotly>=5.22.0
Dynamic: author
Dynamic: author-email
Dynamic: description
Dynamic: description-content-type
Dynamic: home-page
Dynamic: license
Dynamic: requires-dist
Dynamic: requires-python
Dynamic: summary
